pyvis_network/.DS_Store
pyvis_network/__about__.py
pyvis_network/__init__.py
pyvis_network/__pycache__/__about__.cpython-38.pyc
pyvis_network/__pycache__/__init__.cpython-38.pyc
pyvis_network/dataset/.DS_Store
pyvis_network/dataset/__init__.py
pyvis_network/dataset/_dataset.py
pyvis_network/dataset/__pycache__/__init__.cpython-38.pyc
pyvis_network/dataset/__pycache__/_dataset.cpython-38.pyc
pyvis_network/dataset/data/Machine_Learning_edges.csv
pyvis_network/dataset/data/Machine_Learning_nodes.csv
pyvis_network/dataset/data/__init__.py
pyvis_network/dataset/data/example1_edges.csv
pyvis_network/dataset/data/example1_nodes.csv
pyvis_network/dataset/data/__pycache__/__init__.cpython-38.pyc
pyvis_network/examples/.DS_Store
pyvis_network/examples/images/Example1.png
pyvis_network/network/__init__.py
pyvis_network/network/_network.py
pyvis_network/network/__pycache__/__init__.cpython-38.pyc
pyvis_network/network/__pycache__/_network.cpython-38.pyc
pyvis_network-0.0.6.dist-info/LICENSE
pyvis_network-0.0.6.dist-info/METADATA
pyvis_network-0.0.6.dist-info/WHEEL
pyvis_network-0.0.6.dist-info/top_level.txt
pyvis_network-0.0.6.dist-info/RECORD
