Metadata-Version: 2.1
Name: pyvis-network
Version: 0.0.6
Summary: Interactive Network Visualizations
Home-page: https://github.com/daniel-yj-yang/pyvis-network
Author: Daniel Yang
Author-email: daniel.yj.yang@gmail.com
License: BSD-3-Clause License
Platform: UNKNOWN
Classifier: Development Status :: 3 - Alpha
Classifier: Programming Language :: Python :: 3
Classifier: Programming Language :: Python :: 3.8
Classifier: Programming Language :: Python :: 3.9
Classifier: License :: OSI Approved :: BSD License
Classifier: Operating System :: OS Independent
Requires-Python: >=3.8
License-File: LICENSE
